{
 "actions": [],
 "allow_rename": 1,
 "creation": "2025-05-22 15:08:59.193721",
 "doctype": "DocType",
 "editable_grid": 1,
 "engine": "InnoDB",
 "field_order": [
  "code",
  "designation",
  "price",
  "stock",
  "main_category",
  "brand",
  "description_html",
  "imagens",
  "imagem_capa"
 ],
 "fields": [
  {
   "fieldname": "code",
   "fieldtype": "Data",
   "in_list_view": 1,
   "in_preview": 1,
	  "label": "CODE",
	  "read_only": 1
  },
  {
   "fieldname": "designation",
   "fieldtype": "Small Text",
   "in_list_view": 1,
   "in_preview": 1,
	  "label": "DESIGNATION",
	  "read_only": 1
  },
  {
   "fieldname": "price",
   "fieldtype": "Currency",
   "in_preview": 1,
   "label": "PRICE",
	  "read_only": 1,
	  "search_index": 1
  },
  {
   "fieldname": "stock",
   "fieldtype": "Float",
   "in_preview": 1,
	  "label": "STOCK",
	  "read_only": 1,
   "search_index": 1
  },
  {
   "fieldname": "main_category",
   "fieldtype": "Data",
   "in_list_view": 1,
   "in_preview": 1,
	  "label": "CATEGORIA PRINCIPAL ",
	  "read_only": 1
  },
  {
   "fieldname": "brand",
   "fieldtype": "Data",
   "in_list_view": 1,
   "in_preview": 1,
	  "label": "MARCA",
	  "read_only": 1
  },
  {
   "fieldname": "description_html",
   "fieldtype": "Small Text",
   "in_list_view": 1,
   "in_preview": 1,
	  "label": "DESCRICAO",
	  "read_only": 1
  },
  {
   "fieldname": "imagens",
   "fieldtype": "Text",
	  "label": "IMAGENS",
	  "read_only": 1
  },
  {
   "fieldname": "imagem_capa",
   "fieldtype": "Text",
	  "label": "IMAGEM_CAPA",
	  "read_only": 1
  }
 ],
 "index_web_pages_for_search": 1,
 "istable": 1,
 "links": [],
 "modified": "2025-07-17 08:48:09.713994",
 "modified_by": "Administrator",
 "module": "Itec Integrations",
 "name": "Stylus Stock History Item",
 "owner": "Administrator",
 "permissions": [],
 "sort_field": "modified",
 "sort_order": "DESC"
}